physfit/__init__.py
physfit/physfit.py
physfit-0.9.0.dist-info/LICENSE
physfit-0.9.0.dist-info/METADATA
physfit-0.9.0.dist-info/WHEEL
physfit-0.9.0.dist-info/top_level.txt
physfit-0.9.0.dist-info/RECORD
