Metadata-Version: 2.1
Name: physfit
Version: 0.9.0
Summary: Function fitting with errors on x and y
Author-email: Daniel Wagenaar <daw@caltech.edu>
Project-URL: Homepage, https://github.com/wagenadl/physfit
Classifier: Programming Language :: Python :: 3
Classifier: License :: OSI Approved :: GNU General Public License v3 or later (GPLv3+)
Classifier: Operating System :: OS Independent
Requires-Python: >=3.8
License-File: LICENSE
Requires-Dist: numpy
Requires-Dist: scipy
